plot_server/__init__.py
plot_server/__main__.py
plot_server/data_handlers.py
plot_server/request_handler.py
plot_server/server_setup.py
plot_server/utils.py
plot_server/plotly/minimal.html
http_plot_server-0.1.dist-info/LICENSE
http_plot_server-0.1.dist-info/METADATA
http_plot_server-0.1.dist-info/WHEEL
http_plot_server-0.1.dist-info/entry_points.txt
http_plot_server-0.1.dist-info/top_level.txt
http_plot_server-0.1.dist-info/RECORD
