Metadata-Version: 2.1
Name: http-plot-server
Version: 0.1
Summary: A simple and lightweight http server to visualize measurements
Home-page: https://github.com/qbee-io/plot_server
Author: qbee.io
Author-email: pypi@qbee.io
License: MIT
Project-URL: qbee Homepage, https://qbee.io/
Project-URL: qbee Docs, https://qbee.io/docs/
Project-URL: Source, https://github.com/qbee-io/plot_server
Keywords: plot server,visualization,plotly,http,measurements
Platform: UNKNOWN
Classifier: Development Status :: 4 - Beta
Classifier: Intended Audience :: Customer Service
Classifier: Intended Audience :: End Users/Desktop
Classifier: Intended Audience :: Information Technology
Classifier: License :: OSI Approved :: MIT License
Classifier: Operating System :: POSIX :: Linux
Classifier: Programming Language :: Python :: 3 :: Only
Classifier: Programming Language :: Python :: 3.5
Classifier: Programming Language :: Python :: 3.6
Classifier: Programming Language :: Python :: 3.7
Classifier: Programming Language :: Python :: 3.8
Classifier: Programming Language :: Python :: 3.9
Classifier: Programming Language :: Python :: 3.10
Classifier: Programming Language :: JavaScript
Classifier: Topic :: Scientific/Engineering :: Visualization
Classifier: Topic :: Internet :: WWW/HTTP :: HTTP Servers
Classifier: Topic :: Text Processing :: Markup :: HTML
Requires-Python: >=3.5, <4
License-File: LICENSE
Requires-Dist: python-dateutil
